<?xml version="1.0" encoding="UTF-8"?>
<archetype
        xsi:schemaLocation="http://maven.apache.org/plugins/maven-archetype-plugin/archetype-descriptor/1.0.0
        http://maven.apache.org/xsd/archetype-descriptor-1.0.0.xsd"
        xmlns="http://maven.apache.org/plugins/maven-archetype-plugin/archetype-descriptor/1.0.0"
        xmlns:xsi="http://www.w3.org/2001/XMLSchema-instance">
    <id>rd-custom-template</id>
    <requiredProperties>
        <requiredProperty key="artifact-name">
        </requiredProperty>
        <requiredProperty key="client-packageName">
        </requiredProperty>
        <requiredProperty key="client-artifactId">
        </requiredProperty>
        <requiredProperty key="resource-name">
        </requiredProperty>
        <requiredProperty key="resource-name-variable">
        </requiredProperty>
        <requiredProperty key="base-application-path">
        </requiredProperty>
        <requiredProperty key="db-entity-table-name">
        </requiredProperty>
        <requiredProperty key="persistence-unit-name">
        </requiredProperty>
    </requiredProperties>
    <fileSets>
        <fileSet filtered="true" packaged="true" encoding="UTF-8">
            <directory>src/main/java</directory>
        </fileSet>
        <fileSet filtered="true" packaged="true" encoding="UTF-8">
            <directory>src/test/java</directory>
        </fileSet>
        <fileSet filtered="true" encoding="UTF-8">
            <directory>src/main/resources</directory>
        </fileSet>
        <fileSet filtered="true" encoding="UTF-8">
            <directory>
            </directory>
            <includes>
                <include>README.md</include>
                <include>dopackage.sh</include>
                <include>run.sh</include>
            </includes>
        </fileSet>
    </fileSets>
</archetype>



